{
  "version": "v2_wvs_w5_CHN",
  "dataset": "wvs_w5_chn",
  "description": "WVS Wave 5 CHN: 31 constructs, 59 bridges",
  "generated": "2026-04-10T00:18:51.740923",
  "metadata": {
    "wave": 5,
    "country": "CHN",
    "year": 2007,
    "n_constructs": 31,
    "n_bridges": 59,
    "n_domains": 6,
    "n_respondents": 1991,
    "ses_vars": [
      "sexo",
      "edad",
      "escol",
      "Tam_loc"
    ]
  },
  "domains": [
    {
      "id": "WVS_A",
      "label": "Social Values, Attitudes & Stereotypes"
    },
    {
      "id": "WVS_C",
      "label": "Work & Employment"
    },
    {
      "id": "WVS_D",
      "label": "Family"
    },
    {
      "id": "WVS_E",
      "label": "Politics & Society"
    },
    {
      "id": "WVS_F",
      "label": "Religion & Morale"
    },
    {
      "id": "WVS_G",
      "label": "National Identity"
    }
  ],
  "constructs": [
    {
      "id": "WVS_E|authoritarian_governance_tolerance",
      "label": "Authoritarian Governance Tolerance",
      "domain": "WVS_E",
      "column": "wvs_agg_authoritarian_governance_tolerance",
      "rho_escol": 0.0,
      "rho_Tam_loc": -0.006829,
      "rho_sexo": 0.064692,
      "rho_edad": 0.054309,
      "ses_magnitude": 0.048926,
      "dominant_dim": "sexo",
      "ses_sign": 1
    },
    {
      "id": "WVS_E|autocracy_support",
      "label": "Autocracy Support",
      "domain": "WVS_E",
      "column": "wvs_agg_autocracy_support",
      "rho_escol": 0.0,
      "rho_Tam_loc": 0.052859,
      "rho_sexo": -0.026637,
      "rho_edad": 0.012653,
      "ses_magnitude": 0.034946,
      "dominant_dim": "Tam_loc",
      "ses_sign": 1
    },
    {
      "id": "WVS_A|child_qualities_autonomy_self_expression",
      "label": "Child Qualities Autonomy Self Expression",
      "domain": "WVS_A",
      "column": "wvs_agg_child_qualities_autonomy_self_expression",
      "rho_escol": 0.0,
      "rho_Tam_loc": 0.030998,
      "rho_sexo": -0.068018,
      "rho_edad": -0.253015,
      "ses_magnitude": 0.15232,
      "dominant_dim": "edad",
      "ses_sign": 1
    },
    {
      "id": "WVS_A|child_qualities_conformity_tradition",
      "label": "Child Qualities Conformity Tradition",
      "domain": "WVS_A",
      "column": "wvs_agg_child_qualities_conformity_tradition",
      "rho_escol": 0.0,
      "rho_Tam_loc": -0.041819,
      "rho_sexo": 0.00698,
      "rho_edad": -0.068617,
      "ses_magnitude": 0.046568,
      "dominant_dim": "edad",
      "ses_sign": 1
    },
    {
      "id": "WVS_A|child_qualities_prosocial_diligence",
      "label": "Child Qualities Prosocial Diligence",
      "domain": "WVS_A",
      "column": "wvs_agg_child_qualities_prosocial_diligence",
      "rho_escol": 0.0,
      "rho_Tam_loc": -0.026642,
      "rho_sexo": -0.012183,
      "rho_edad": 0.046886,
      "ses_magnitude": 0.031919,
      "dominant_dim": "edad",
      "ses_sign": 1
    },
    {
      "id": "WVS_F|civic_dishonesty_tolerance",
      "label": "Civic Dishonesty Tolerance",
      "domain": "WVS_F",
      "column": "wvs_agg_civic_dishonesty_tolerance",
      "rho_escol": 0.0,
      "rho_Tam_loc": -0.104039,
      "rho_sexo": 0.004792,
      "rho_edad": -0.061373,
      "ses_magnitude": 0.069794,
      "dominant_dim": "Tam_loc",
      "ses_sign": 1
    },
    {
      "id": "WVS_E|confidence_in_civil_society_organizations",
      "label": "Confidence In Civil Society Organizations",
      "domain": "WVS_E",
      "column": "wvs_agg_confidence_in_civil_society_organizations",
      "rho_escol": 0.0,
      "rho_Tam_loc": -0.008385,
      "rho_sexo": -0.014126,
      "rho_edad": -0.06716,
      "ses_magnitude": 0.039918,
      "dominant_dim": "edad",
      "ses_sign": 1
    },
    {
      "id": "WVS_E|confidence_in_domestic_institutions",
      "label": "Confidence In Domestic Institutions",
      "domain": "WVS_E",
      "column": "wvs_agg_confidence_in_domestic_institutions",
      "rho_escol": 0.0,
      "rho_Tam_loc": 0.1028,
      "rho_sexo": -0.005709,
      "rho_edad": -0.164873,
      "ses_magnitude": 0.112225,
      "dominant_dim": "edad",
      "ses_sign": 1
    },
    {
      "id": "WVS_E|confidence_in_international_organizations",
      "label": "Confidence In International Organizations",
      "domain": "WVS_E",
      "column": "wvs_agg_confidence_in_international_organizations",
      "rho_escol": 0.0,
      "rho_Tam_loc": -0.004969,
      "rho_sexo": 0.030949,
      "rho_edad": -0.161912,
      "ses_magnitude": 0.095216,
      "dominant_dim": "edad",
      "ses_sign": 1
    },
    {
      "id": "WVS_E|democratic_system_evaluation",
      "label": "Democratic System Evaluation",
      "domain": "WVS_E",
      "column": "wvs_agg_democratic_system_evaluation",
      "rho_escol": 0.0,
      "rho_Tam_loc": -0.001894,
      "rho_sexo": -0.114566,
      "rho_edad": -0.004737,
      "ses_magnitude": 0.06621,
      "dominant_dim": "sexo",
      "ses_sign": 1
    },
    {
      "id": "WVS_E|democratic_values_importance",
      "label": "Democratic Values Importance",
      "domain": "WVS_E",
      "column": "wvs_agg_democratic_values_importance",
      "rho_escol": 0.0,
      "rho_Tam_loc": 0.034705,
      "rho_sexo": -0.006351,
      "rho_edad": 0.112181,
      "ses_magnitude": 0.067895,
      "dominant_dim": "edad",
      "ses_sign": 1
    },
    {
      "id": "WVS_E|economic_ideology",
      "label": "Economic Ideology",
      "domain": "WVS_E",
      "column": "wvs_agg_economic_ideology",
      "rho_escol": 0.0,
      "rho_Tam_loc": 0.039006,
      "rho_sexo": -0.022113,
      "rho_edad": 0.039272,
      "ses_magnitude": 0.034413,
      "dominant_dim": "edad",
      "ses_sign": 1
    },
    {
      "id": "WVS_D|gender_role_traditionalism",
      "label": "Gender Role Traditionalism",
      "domain": "WVS_D",
      "column": "wvs_agg_gender_role_traditionalism",
      "rho_escol": 0.0,
      "rho_Tam_loc": 0.018618,
      "rho_sexo": 0.088681,
      "rho_edad": -0.053361,
      "ses_magnitude": 0.060713,
      "dominant_dim": "sexo",
      "ses_sign": 1
    },
    {
      "id": "WVS_G|immigrant_origin_status",
      "label": "Immigrant Origin Status",
      "domain": "WVS_G",
      "column": "wvs_agg_immigrant_origin_status",
      "rho_escol": 0.0,
      "rho_Tam_loc": 0.0,
      "rho_sexo": 0.0,
      "rho_edad": 0.0,
      "ses_magnitude": 0.0,
      "dominant_dim": "escol",
      "ses_sign": 1
    },
    {
      "id": "WVS_A|importance_of_life_domains",
      "label": "Importance Of Life Domains",
      "domain": "WVS_A",
      "column": "wvs_agg_importance_of_life_domains",
      "rho_escol": 0.0,
      "rho_Tam_loc": 0.021565,
      "rho_sexo": -0.098332,
      "rho_edad": -0.133709,
      "ses_magnitude": 0.09663,
      "dominant_dim": "edad",
      "ses_sign": 1
    },
    {
      "id": "WVS_C|job_scarcity_gender_discrimination",
      "label": "Job Scarcity Gender Discrimination",
      "domain": "WVS_C",
      "column": "wvs_agg_job_scarcity_gender_discrimination",
      "rho_escol": 0.0,
      "rho_Tam_loc": -0.024244,
      "rho_sexo": 0.011897,
      "rho_edad": -0.051992,
      "ses_magnitude": 0.033825,
      "dominant_dim": "edad",
      "ses_sign": 1
    },
    {
      "id": "WVS_C|job_scarcity_nativist_preference",
      "label": "Job Scarcity Nativist Preference",
      "domain": "WVS_C",
      "column": "wvs_agg_job_scarcity_nativist_preference",
      "rho_escol": 0.0,
      "rho_Tam_loc": -0.007916,
      "rho_sexo": -0.013126,
      "rho_edad": -0.063894,
      "ses_magnitude": 0.037936,
      "dominant_dim": "edad",
      "ses_sign": 1
    },
    {
      "id": "WVS_F|life_autonomy_morality_permissiveness",
      "label": "Life Autonomy Morality Permissiveness",
      "domain": "WVS_F",
      "column": "wvs_agg_life_autonomy_morality_permissiveness",
      "rho_escol": 0.0,
      "rho_Tam_loc": 0.038674,
      "rho_sexo": -0.030863,
      "rho_edad": -0.04098,
      "ses_magnitude": 0.037093,
      "dominant_dim": "edad",
      "ses_sign": 1
    },
    {
      "id": "WVS_E|offline_political_participation",
      "label": "Offline Political Participation",
      "domain": "WVS_E",
      "column": "wvs_agg_offline_political_participation",
      "rho_escol": 0.0,
      "rho_Tam_loc": 0.025308,
      "rho_sexo": -0.065024,
      "rho_edad": -0.091653,
      "ses_magnitude": 0.066505,
      "dominant_dim": "edad",
      "ses_sign": 1
    },
    {
      "id": "WVS_G|outgroup_trust",
      "label": "Outgroup Trust",
      "domain": "WVS_G",
      "column": "wvs_agg_outgroup_trust",
      "rho_escol": 0.0,
      "rho_Tam_loc": 0.08372,
      "rho_sexo": -0.060971,
      "rho_edad": 0.029872,
      "ses_magnitude": 0.062233,
      "dominant_dim": "Tam_loc",
      "ses_sign": 1
    },
    {
      "id": "WVS_E|postmaterialist_values",
      "label": "Postmaterialist Values",
      "domain": "WVS_E",
      "column": "wvs_agg_postmaterialist_values",
      "rho_escol": 0.0,
      "rho_Tam_loc": 0.026221,
      "rho_sexo": -0.089128,
      "rho_edad": -0.09773,
      "ses_magnitude": 0.077851,
      "dominant_dim": "edad",
      "ses_sign": 1
    },
    {
      "id": "WVS_F|religious_belief",
      "label": "Religious Belief",
      "domain": "WVS_F",
      "column": "wvs_agg_religious_belief",
      "rho_escol": 0.0,
      "rho_Tam_loc": 0.00697,
      "rho_sexo": 0.09334,
      "rho_edad": -0.027209,
      "ses_magnitude": 0.056277,
      "dominant_dim": "sexo",
      "ses_sign": 1
    },
    {
      "id": "WVS_F|religious_practice_and_self_identification",
      "label": "Religious Practice And Self Identification",
      "domain": "WVS_F",
      "column": "wvs_agg_religious_practice_and_self_identification",
      "rho_escol": 0.0,
      "rho_Tam_loc": 0.001276,
      "rho_sexo": 0.006589,
      "rho_edad": -0.043101,
      "ses_magnitude": 0.025184,
      "dominant_dim": "edad",
      "ses_sign": 1
    },
    {
      "id": "WVS_E|science_technology_optimism",
      "label": "Science Technology Optimism",
      "domain": "WVS_E",
      "column": "wvs_agg_science_technology_optimism",
      "rho_escol": 0.0,
      "rho_Tam_loc": 0.003307,
      "rho_sexo": -0.026388,
      "rho_edad": 0.098817,
      "ses_magnitude": 0.059082,
      "dominant_dim": "edad",
      "ses_sign": 1
    },
    {
      "id": "WVS_F|sexual_and_reproductive_morality_permissiveness",
      "label": "Sexual And Reproductive Morality Permissiveness",
      "domain": "WVS_F",
      "column": "wvs_agg_sexual_and_reproductive_morality_permissiveness",
      "rho_escol": 0.0,
      "rho_Tam_loc": 0.044233,
      "rho_sexo": 0.012565,
      "rho_edad": -0.015401,
      "ses_magnitude": 0.027998,
      "dominant_dim": "Tam_loc",
      "ses_sign": 1
    },
    {
      "id": "WVS_A|social_intolerance_outgroups",
      "label": "Social Intolerance Outgroups",
      "domain": "WVS_A",
      "column": "wvs_agg_social_intolerance_outgroups",
      "rho_escol": 0.0,
      "rho_Tam_loc": -0.154192,
      "rho_sexo": 0.011272,
      "rho_edad": 0.032233,
      "ses_magnitude": 0.09118,
      "dominant_dim": "Tam_loc",
      "ses_sign": 1
    },
    {
      "id": "WVS_E|societal_change_attitudes",
      "label": "Societal Change Attitudes",
      "domain": "WVS_E",
      "column": "wvs_agg_societal_change_attitudes",
      "rho_escol": 0.0,
      "rho_Tam_loc": -0.017271,
      "rho_sexo": 0.009476,
      "rho_edad": -0.046297,
      "ses_magnitude": 0.029049,
      "dominant_dim": "edad",
      "ses_sign": 1
    },
    {
      "id": "WVS_A|subjective_wellbeing",
      "label": "Subjective Wellbeing",
      "domain": "WVS_A",
      "column": "wvs_agg_subjective_wellbeing",
      "rho_escol": 0.0,
      "rho_Tam_loc": -0.024077,
      "rho_sexo": -0.045908,
      "rho_edad": -0.006125,
      "ses_magnitude": 0.030137,
      "dominant_dim": "sexo",
      "ses_sign": 1
    },
    {
      "id": "WVS_F|violence_tolerance",
      "label": "Violence Tolerance",
      "domain": "WVS_F",
      "column": "wvs_agg_violence_tolerance",
      "rho_escol": 0.0,
      "rho_Tam_loc": 0.001764,
      "rho_sexo": -0.074685,
      "rho_edad": 0.029931,
      "ses_magnitude": 0.046464,
      "dominant_dim": "sexo",
      "ses_sign": 1
    },
    {
      "id": "WVS_A|voluntary_association_active_membership",
      "label": "Voluntary Association Active Membership",
      "domain": "WVS_A",
      "column": "wvs_agg_voluntary_association_active_membership",
      "rho_escol": 0.0,
      "rho_Tam_loc": 0.004721,
      "rho_sexo": -0.049473,
      "rho_edad": -0.128637,
      "ses_magnitude": 0.079619,
      "dominant_dim": "edad",
      "ses_sign": 1
    },
    {
      "id": "WVS_C|work_ethic",
      "label": "Work Ethic",
      "domain": "WVS_C",
      "column": "wvs_agg_work_ethic",
      "rho_escol": 0.0,
      "rho_Tam_loc": 0.046028,
      "rho_sexo": 0.046987,
      "rho_edad": -0.140348,
      "ses_magnitude": 0.089487,
      "dominant_dim": "edad",
      "ses_sign": 1
    }
  ],
  "relationships": [],
  "bridges": [
    {
      "from": "WVS_E|authoritarian_governance_tolerance",
      "to": "WVS_A|importance_of_life_domains",
      "gamma": -0.0169,
      "ci_lo": -0.0333,
      "ci_hi": -0.001,
      "ci_width": 0.0323,
      "excl_zero": true,
      "nmi": 0.0001,
      "fingerprint_dot": -0.01377,
      "fingerprint_cos": -0.970884,
      "dot_sign_consistent": true
    },
    {
      "from": "WVS_E|authoritarian_governance_tolerance",
      "to": "WVS_F|life_autonomy_morality_permissiveness",
      "gamma": -0.0107,
      "ci_lo": -0.0249,
      "ci_hi": -0.0004,
      "ci_width": 0.0245,
      "excl_zero": true,
      "nmi": 0.0,
      "fingerprint_dot": -0.004486,
      "fingerprint_cos": -0.824028,
      "dot_sign_consistent": true
    },
    {
      "from": "WVS_E|autocracy_support",
      "to": "WVS_F|civic_dishonesty_tolerance",
      "gamma": -0.0119,
      "ci_lo": -0.0248,
      "ci_hi": -0.0033,
      "ci_width": 0.0215,
      "excl_zero": true,
      "nmi": 0.0,
      "fingerprint_dot": -0.006404,
      "fingerprint_cos": -0.875152,
      "dot_sign_consistent": true
    },
    {
      "from": "WVS_A|child_qualities_autonomy_self_expression",
      "to": "WVS_F|civic_dishonesty_tolerance",
      "gamma": 0.0222,
      "ci_lo": 0.0051,
      "ci_hi": 0.0425,
      "ci_width": 0.0373,
      "excl_zero": true,
      "nmi": 0.0001,
      "fingerprint_dot": 0.011977,
      "fingerprint_cos": 0.375546,
      "dot_sign_consistent": true
    },
    {
      "from": "WVS_A|child_qualities_autonomy_self_expression",
      "to": "WVS_E|confidence_in_civil_society_organizations",
      "gamma": 0.0186,
      "ci_lo": 0.0001,
      "ci_hi": 0.0416,
      "ci_width": 0.0415,
      "excl_zero": true,
      "nmi": 0.0001,
      "fingerprint_dot": 0.017693,
      "fingerprint_cos": 0.969987,
      "dot_sign_consistent": true
    },
    {
      "from": "WVS_A|child_qualities_autonomy_self_expression",
      "to": "WVS_E|confidence_in_domestic_institutions",
      "gamma": 0.0308,
      "ci_lo": 0.0108,
      "ci_hi": 0.0506,
      "ci_width": 0.0397,
      "excl_zero": true,
      "nmi": 0.0003,
      "fingerprint_dot": 0.04529,
      "fingerprint_cos": 0.883154,
      "dot_sign_consistent": true
    },
    {
      "from": "WVS_A|child_qualities_autonomy_self_expression",
      "to": "WVS_E|confidence_in_international_organizations",
      "gamma": 0.0451,
      "ci_lo": 0.0176,
      "ci_hi": 0.0771,
      "ci_width": 0.0595,
      "excl_zero": true,
      "nmi": 0.0005,
      "fingerprint_dot": 0.038707,
      "fingerprint_cos": 0.88962,
      "dot_sign_consistent": true
    },
    {
      "from": "WVS_A|child_qualities_autonomy_self_expression",
      "to": "WVS_E|democratic_values_importance",
      "gamma": -0.0317,
      "ci_lo": -0.0516,
      "ci_hi": -0.015,
      "ci_width": 0.0366,
      "excl_zero": true,
      "nmi": 0.0003,
      "fingerprint_dot": -0.026876,
      "fingerprint_cos": -0.866248,
      "dot_sign_consistent": true
    },
    {
      "from": "WVS_A|child_qualities_autonomy_self_expression",
      "to": "WVS_C|job_scarcity_gender_discrimination",
      "gamma": 0.0193,
      "ci_lo": 0.0015,
      "ci_hi": 0.0364,
      "ci_width": 0.0349,
      "excl_zero": true,
      "nmi": 0.0001,
      "fingerprint_dot": 0.011594,
      "fingerprint_cos": 0.750091,
      "dot_sign_consistent": true
    },
    {
      "from": "WVS_A|child_qualities_autonomy_self_expression",
      "to": "WVS_C|job_scarcity_nativist_preference",
      "gamma": 0.031,
      "ci_lo": 0.0071,
      "ci_hi": 0.0521,
      "ci_width": 0.0449,
      "excl_zero": true,
      "nmi": 0.0002,
      "fingerprint_dot": 0.016814,
      "fingerprint_cos": 0.969911,
      "dot_sign_consistent": true
    },
    {
      "from": "WVS_A|child_qualities_autonomy_self_expression",
      "to": "WVS_E|offline_political_participation",
      "gamma": 0.072,
      "ci_lo": 0.0339,
      "ci_hi": 0.1143,
      "ci_width": 0.0804,
      "excl_zero": true,
      "nmi": 0.0009,
      "fingerprint_dot": 0.028397,
      "fingerprint_cos": 0.934408,
      "dot_sign_consistent": true
    },
    {
      "from": "WVS_A|child_qualities_autonomy_self_expression",
      "to": "WVS_E|postmaterialist_values",
      "gamma": 0.0283,
      "ci_lo": 0.0095,
      "ci_hi": 0.0468,
      "ci_width": 0.0373,
      "excl_zero": true,
      "nmi": 0.0002,
      "fingerprint_dot": 0.031602,
      "fingerprint_cos": 0.888331,
      "dot_sign_consistent": true
    },
    {
      "from": "WVS_A|child_qualities_autonomy_self_expression",
      "to": "WVS_E|science_technology_optimism",
      "gamma": -0.0317,
      "ci_lo": -0.0489,
      "ci_hi": -0.0146,
      "ci_width": 0.0343,
      "excl_zero": true,
      "nmi": 0.0003,
      "fingerprint_dot": -0.023105,
      "fingerprint_cos": -0.855795,
      "dot_sign_consistent": true
    },
    {
      "from": "WVS_A|child_qualities_autonomy_self_expression",
      "to": "WVS_C|work_ethic",
      "gamma": 0.0442,
      "ci_lo": 0.0284,
      "ci_hi": 0.0632,
      "ci_width": 0.0348,
      "excl_zero": true,
      "nmi": 0.0006,
      "fingerprint_dot": 0.033741,
      "fingerprint_cos": 0.825123,
      "dot_sign_consistent": true
    },
    {
      "from": "WVS_A|child_qualities_conformity_tradition",
      "to": "WVS_F|civic_dishonesty_tolerance",
      "gamma": 0.0148,
      "ci_lo": 0.0012,
      "ci_hi": 0.027,
      "ci_width": 0.0258,
      "excl_zero": true,
      "nmi": 0.0001,
      "fingerprint_dot": 0.008595,
      "fingerprint_cos": 0.881532,
      "dot_sign_consistent": true
    },
    {
      "from": "WVS_A|child_qualities_prosocial_diligence",
      "to": "WVS_E|confidence_in_domestic_institutions",
      "gamma": -0.0197,
      "ci_lo": -0.0345,
      "ci_hi": -0.0083,
      "ci_width": 0.0262,
      "excl_zero": true,
      "nmi": 0.0001,
      "fingerprint_dot": -0.010399,
      "fingerprint_cos": -0.967713,
      "dot_sign_consistent": true
    },
    {
      "from": "WVS_A|child_qualities_prosocial_diligence",
      "to": "WVS_E|democratic_values_importance",
      "gamma": 0.0125,
      "ci_lo": 0.0031,
      "ci_hi": 0.0266,
      "ci_width": 0.0235,
      "excl_zero": true,
      "nmi": 0.0,
      "fingerprint_dot": 0.004412,
      "fingerprint_cos": 0.678685,
      "dot_sign_consistent": true
    },
    {
      "from": "WVS_A|child_qualities_prosocial_diligence",
      "to": "WVS_E|offline_political_participation",
      "gamma": -0.0241,
      "ci_lo": -0.0526,
      "ci_hi": -0.0016,
      "ci_width": 0.051,
      "excl_zero": true,
      "nmi": 0.0001,
      "fingerprint_dot": -0.004179,
      "fingerprint_cos": -0.656257,
      "dot_sign_consistent": true
    },
    {
      "from": "WVS_A|child_qualities_prosocial_diligence",
      "to": "WVS_F|religious_belief",
      "gamma": -0.0113,
      "ci_lo": -0.0239,
      "ci_hi": -0.0012,
      "ci_width": 0.0227,
      "excl_zero": true,
      "nmi": 0.0,
      "fingerprint_dot": -0.002599,
      "fingerprint_cos": -0.482205,
      "dot_sign_consistent": true
    },
    {
      "from": "WVS_A|child_qualities_prosocial_diligence",
      "to": "WVS_C|work_ethic",
      "gamma": -0.0236,
      "ci_lo": -0.036,
      "ci_hi": -0.0126,
      "ci_width": 0.0234,
      "excl_zero": true,
      "nmi": 0.0002,
      "fingerprint_dot": -0.008379,
      "fingerprint_cos": -0.977824,
      "dot_sign_consistent": true
    },
    {
      "from": "WVS_F|civic_dishonesty_tolerance",
      "to": "WVS_E|confidence_in_international_organizations",
      "gamma": 0.0171,
      "ci_lo": 0.0042,
      "ci_hi": 0.0373,
      "ci_width": 0.0331,
      "excl_zero": true,
      "nmi": 0.0001,
      "fingerprint_dot": 0.010602,
      "fingerprint_cos": 0.531803,
      "dot_sign_consistent": true
    },
    {
      "from": "WVS_F|civic_dishonesty_tolerance",
      "to": "WVS_E|democratic_values_importance",
      "gamma": -0.0133,
      "ci_lo": -0.0267,
      "ci_hi": -0.0052,
      "ci_width": 0.0215,
      "excl_zero": true,
      "nmi": 0.0001,
      "fingerprint_dot": -0.010526,
      "fingerprint_cos": -0.740426,
      "dot_sign_consistent": true
    },
    {
      "from": "WVS_F|civic_dishonesty_tolerance",
      "to": "WVS_C|job_scarcity_gender_discrimination",
      "gamma": 0.0132,
      "ci_lo": 0.0025,
      "ci_hi": 0.0222,
      "ci_width": 0.0197,
      "excl_zero": true,
      "nmi": 0.0001,
      "fingerprint_dot": 0.00577,
      "fingerprint_cos": 0.814722,
      "dot_sign_consistent": true
    },
    {
      "from": "WVS_F|civic_dishonesty_tolerance",
      "to": "WVS_G|outgroup_trust",
      "gamma": -0.0114,
      "ci_lo": -0.0225,
      "ci_hi": -0.0012,
      "ci_width": 0.0213,
      "excl_zero": true,
      "nmi": 0.0,
      "fingerprint_dot": -0.010836,
      "fingerprint_cos": -0.831559,
      "dot_sign_consistent": true
    },
    {
      "from": "WVS_F|civic_dishonesty_tolerance",
      "to": "WVS_A|social_intolerance_outgroups",
      "gamma": 0.02,
      "ci_lo": 0.0044,
      "ci_hi": 0.0314,
      "ci_width": 0.027,
      "excl_zero": true,
      "nmi": 0.0001,
      "fingerprint_dot": 0.014118,
      "fingerprint_cos": 0.739481,
      "dot_sign_consistent": true
    },
    {
      "from": "WVS_E|confidence_in_domestic_institutions",
      "to": "WVS_A|importance_of_life_domains",
      "gamma": 0.0164,
      "ci_lo": 0.0039,
      "ci_hi": 0.0302,
      "ci_width": 0.0263,
      "excl_zero": true,
      "nmi": 0.0001,
      "fingerprint_dot": 0.024823,
      "fingerprint_cos": 0.763015,
      "dot_sign_consistent": true
    },
    {
      "from": "WVS_E|confidence_in_domestic_institutions",
      "to": "WVS_G|outgroup_trust",
      "gamma": 0.0118,
      "ci_lo": 0.0002,
      "ci_hi": 0.0214,
      "ci_width": 0.0211,
      "excl_zero": true,
      "nmi": 0.0,
      "fingerprint_dot": 0.004029,
      "fingerprint_cos": 0.192313,
      "dot_sign_consistent": true
    },
    {
      "from": "WVS_E|confidence_in_domestic_institutions",
      "to": "WVS_A|social_intolerance_outgroups",
      "gamma": -0.0222,
      "ci_lo": -0.0343,
      "ci_hi": -0.0094,
      "ci_width": 0.0249,
      "excl_zero": true,
      "nmi": 0.0002,
      "fingerprint_dot": -0.02123,
      "fingerprint_cos": -0.691564,
      "dot_sign_consistent": true
    },
    {
      "from": "WVS_E|confidence_in_domestic_institutions",
      "to": "WVS_C|work_ethic",
      "gamma": 0.0235,
      "ci_lo": 0.0129,
      "ci_hi": 0.0352,
      "ci_width": 0.0223,
      "excl_zero": true,
      "nmi": 0.0002,
      "fingerprint_dot": 0.027603,
      "fingerprint_cos": 0.916186,
      "dot_sign_consistent": true
    },
    {
      "from": "WVS_E|confidence_in_international_organizations",
      "to": "WVS_A|importance_of_life_domains",
      "gamma": 0.0221,
      "ci_lo": 0.0033,
      "ci_hi": 0.0428,
      "ci_width": 0.0396,
      "excl_zero": true,
      "nmi": 0.0001,
      "fingerprint_dot": 0.018499,
      "fingerprint_cos": 0.670188,
      "dot_sign_consistent": true
    },
    {
      "from": "WVS_E|confidence_in_international_organizations",
      "to": "WVS_C|job_scarcity_gender_discrimination",
      "gamma": 0.0151,
      "ci_lo": 0.001,
      "ci_hi": 0.0318,
      "ci_width": 0.0308,
      "excl_zero": true,
      "nmi": 0.0001,
      "fingerprint_dot": 0.008907,
      "fingerprint_cos": 0.921826,
      "dot_sign_consistent": true
    },
    {
      "from": "WVS_E|confidence_in_international_organizations",
      "to": "WVS_C|job_scarcity_nativist_preference",
      "gamma": 0.017,
      "ci_lo": 0.0041,
      "ci_hi": 0.0345,
      "ci_width": 0.0305,
      "excl_zero": true,
      "nmi": 0.0001,
      "fingerprint_dot": 0.009978,
      "fingerprint_cos": 0.920825,
      "dot_sign_consistent": true
    },
    {
      "from": "WVS_E|confidence_in_international_organizations",
      "to": "WVS_C|work_ethic",
      "gamma": 0.0219,
      "ci_lo": 0.0057,
      "ci_hi": 0.0448,
      "ci_width": 0.0391,
      "excl_zero": true,
      "nmi": 0.0001,
      "fingerprint_dot": 0.02395,
      "fingerprint_cos": 0.936928,
      "dot_sign_consistent": true
    },
    {
      "from": "WVS_E|democratic_system_evaluation",
      "to": "WVS_D|gender_role_traditionalism",
      "gamma": -0.0124,
      "ci_lo": -0.0242,
      "ci_hi": -0.0018,
      "ci_width": 0.0224,
      "excl_zero": true,
      "nmi": 0.0,
      "fingerprint_dot": -0.009942,
      "fingerprint_cos": -0.824436,
      "dot_sign_consistent": true
    },
    {
      "from": "WVS_E|democratic_system_evaluation",
      "to": "WVS_F|religious_belief",
      "gamma": -0.0178,
      "ci_lo": -0.0357,
      "ci_hi": -0.0049,
      "ci_width": 0.0308,
      "excl_zero": true,
      "nmi": 0.0001,
      "fingerprint_dot": -0.010578,
      "fingerprint_cos": -0.946287,
      "dot_sign_consistent": true
    },
    {
      "from": "WVS_E|democratic_system_evaluation",
      "to": "WVS_A|subjective_wellbeing",
      "gamma": 0.0106,
      "ci_lo": 0.0004,
      "ci_hi": 0.022,
      "ci_width": 0.0215,
      "excl_zero": true,
      "nmi": 0.0,
      "fingerprint_dot": 0.005334,
      "fingerprint_cos": 0.89107,
      "dot_sign_consistent": true
    },
    {
      "from": "WVS_E|democratic_values_importance",
      "to": "WVS_A|importance_of_life_domains",
      "gamma": -0.0154,
      "ci_lo": -0.029,
      "ci_hi": -0.0057,
      "ci_width": 0.0234,
      "excl_zero": true,
      "nmi": 0.0001,
      "fingerprint_dot": -0.013627,
      "fingerprint_cos": -0.692333,
      "dot_sign_consistent": true
    },
    {
      "from": "WVS_E|democratic_values_importance",
      "to": "WVS_C|job_scarcity_nativist_preference",
      "gamma": -0.012,
      "ci_lo": -0.0237,
      "ci_hi": -0.0039,
      "ci_width": 0.0198,
      "excl_zero": true,
      "nmi": 0.0,
      "fingerprint_dot": -0.007359,
      "fingerprint_cos": -0.95238,
      "dot_sign_consistent": true
    },
    {
      "from": "WVS_E|democratic_values_importance",
      "to": "WVS_C|work_ethic",
      "gamma": -0.0173,
      "ci_lo": -0.03,
      "ci_hi": -0.0074,
      "ci_width": 0.0226,
      "excl_zero": true,
      "nmi": 0.0001,
      "fingerprint_dot": -0.014445,
      "fingerprint_cos": -0.792513,
      "dot_sign_consistent": true
    },
    {
      "from": "WVS_D|gender_role_traditionalism",
      "to": "WVS_F|religious_belief",
      "gamma": 0.0118,
      "ci_lo": 0.0004,
      "ci_hi": 0.0264,
      "ci_width": 0.026,
      "excl_zero": true,
      "nmi": 0.0,
      "fingerprint_dot": 0.009859,
      "fingerprint_cos": 0.961842,
      "dot_sign_consistent": true
    },
    {
      "from": "WVS_D|gender_role_traditionalism",
      "to": "WVS_E|science_technology_optimism",
      "gamma": -0.0096,
      "ci_lo": -0.0195,
      "ci_hi": -0.0008,
      "ci_width": 0.0187,
      "excl_zero": true,
      "nmi": 0.0,
      "fingerprint_dot": -0.007552,
      "fingerprint_cos": -0.701735,
      "dot_sign_consistent": true
    },
    {
      "from": "WVS_D|gender_role_traditionalism",
      "to": "WVS_C|work_ethic",
      "gamma": 0.0132,
      "ci_lo": 0.0028,
      "ci_hi": 0.0265,
      "ci_width": 0.0236,
      "excl_zero": true,
      "nmi": 0.0001,
      "fingerprint_dot": 0.012513,
      "fingerprint_cos": 0.7677,
      "dot_sign_consistent": true
    },
    {
      "from": "WVS_A|importance_of_life_domains",
      "to": "WVS_C|job_scarcity_nativist_preference",
      "gamma": 0.0161,
      "ci_lo": 0.0019,
      "ci_hi": 0.0319,
      "ci_width": 0.03,
      "excl_zero": true,
      "nmi": 0.0001,
      "fingerprint_dot": 0.009663,
      "fingerprint_cos": 0.878689,
      "dot_sign_consistent": true
    },
    {
      "from": "WVS_A|importance_of_life_domains",
      "to": "WVS_E|offline_political_participation",
      "gamma": 0.0497,
      "ci_lo": 0.0246,
      "ci_hi": 0.0742,
      "ci_width": 0.0496,
      "excl_zero": true,
      "nmi": 0.0005,
      "fingerprint_dot": 0.019195,
      "fingerprint_cos": 0.995602,
      "dot_sign_consistent": true
    },
    {
      "from": "WVS_A|importance_of_life_domains",
      "to": "WVS_E|postmaterialist_values",
      "gamma": 0.0186,
      "ci_lo": 0.0076,
      "ci_hi": 0.0312,
      "ci_width": 0.0236,
      "excl_zero": true,
      "nmi": 0.0001,
      "fingerprint_dot": 0.022397,
      "fingerprint_cos": 0.992403,
      "dot_sign_consistent": true
    },
    {
      "from": "WVS_A|importance_of_life_domains",
      "to": "WVS_E|science_technology_optimism",
      "gamma": -0.0181,
      "ci_lo": -0.0321,
      "ci_hi": -0.0051,
      "ci_width": 0.027,
      "excl_zero": true,
      "nmi": 0.0001,
      "fingerprint_dot": -0.010547,
      "fingerprint_cos": -0.615776,
      "dot_sign_consistent": true
    },
    {
      "from": "WVS_A|importance_of_life_domains",
      "to": "WVS_C|work_ethic",
      "gamma": 0.0227,
      "ci_lo": 0.0077,
      "ci_hi": 0.0353,
      "ci_width": 0.0276,
      "excl_zero": true,
      "nmi": 0.0002,
      "fingerprint_dot": 0.015138,
      "fingerprint_cos": 0.583544,
      "dot_sign_consistent": true
    },
    {
      "from": "WVS_C|job_scarcity_gender_discrimination",
      "to": "WVS_E|science_technology_optimism",
      "gamma": -0.011,
      "ci_lo": -0.0195,
      "ci_hi": -0.0025,
      "ci_width": 0.017,
      "excl_zero": true,
      "nmi": 0.0,
      "fingerprint_dot": -0.005532,
      "fingerprint_cos": -0.922671,
      "dot_sign_consistent": true
    },
    {
      "from": "WVS_C|job_scarcity_gender_discrimination",
      "to": "WVS_E|societal_change_attitudes",
      "gamma": 0.0114,
      "ci_lo": 0.0015,
      "ci_hi": 0.0208,
      "ci_width": 0.0193,
      "excl_zero": true,
      "nmi": 0.0,
      "fingerprint_dot": 0.002939,
      "fingerprint_cos": 0.996867,
      "dot_sign_consistent": true
    },
    {
      "from": "WVS_C|job_scarcity_nativist_preference",
      "to": "WVS_E|science_technology_optimism",
      "gamma": -0.0122,
      "ci_lo": -0.0251,
      "ci_hi": -0.0031,
      "ci_width": 0.022,
      "excl_zero": true,
      "nmi": 0.0,
      "fingerprint_dot": -0.005994,
      "fingerprint_cos": -0.891379,
      "dot_sign_consistent": true
    },
    {
      "from": "WVS_F|life_autonomy_morality_permissiveness",
      "to": "WVS_E|offline_political_participation",
      "gamma": 0.0243,
      "ci_lo": 0.0065,
      "ci_hi": 0.049,
      "ci_width": 0.0424,
      "excl_zero": true,
      "nmi": 0.0001,
      "fingerprint_dot": 0.006742,
      "fingerprint_cos": 0.910951,
      "dot_sign_consistent": true
    },
    {
      "from": "WVS_F|life_autonomy_morality_permissiveness",
      "to": "WVS_E|postmaterialist_values",
      "gamma": 0.0135,
      "ci_lo": 0.0025,
      "ci_hi": 0.0263,
      "ci_width": 0.0238,
      "excl_zero": true,
      "nmi": 0.0,
      "fingerprint_dot": 0.00777,
      "fingerprint_cos": 0.896884,
      "dot_sign_consistent": true
    },
    {
      "from": "WVS_F|life_autonomy_morality_permissiveness",
      "to": "WVS_A|subjective_wellbeing",
      "gamma": 0.0112,
      "ci_lo": 0.0026,
      "ci_hi": 0.0204,
      "ci_width": 0.0178,
      "excl_zero": true,
      "nmi": 0.0,
      "fingerprint_dot": 0.000737,
      "fingerprint_cos": 0.219677,
      "dot_sign_consistent": true
    },
    {
      "from": "WVS_E|offline_political_participation",
      "to": "WVS_C|work_ethic",
      "gamma": 0.0326,
      "ci_lo": 0.005,
      "ci_hi": 0.0608,
      "ci_width": 0.0558,
      "excl_zero": true,
      "nmi": 0.0002,
      "fingerprint_dot": 0.010973,
      "fingerprint_cos": 0.614586,
      "dot_sign_consistent": true
    },
    {
      "from": "WVS_G|outgroup_trust",
      "to": "WVS_A|social_intolerance_outgroups",
      "gamma": -0.0176,
      "ci_lo": -0.0275,
      "ci_hi": -0.0048,
      "ci_width": 0.0227,
      "excl_zero": true,
      "nmi": 0.0001,
      "fingerprint_dot": -0.012633,
      "fingerprint_cos": -0.742128,
      "dot_sign_consistent": true
    },
    {
      "from": "WVS_E|postmaterialist_values",
      "to": "WVS_A|subjective_wellbeing",
      "gamma": 0.0089,
      "ci_lo": 0.0008,
      "ci_hi": 0.0186,
      "ci_width": 0.0179,
      "excl_zero": true,
      "nmi": 0.0,
      "fingerprint_dot": 0.004059,
      "fingerprint_cos": 0.576665,
      "dot_sign_consistent": true
    },
    {
      "from": "WVS_F|religious_belief",
      "to": "WVS_A|subjective_wellbeing",
      "gamma": -0.0111,
      "ci_lo": -0.0246,
      "ci_hi": -0.0004,
      "ci_width": 0.0242,
      "excl_zero": true,
      "nmi": 0.0,
      "fingerprint_dot": -0.004286,
      "fingerprint_cos": -0.842401,
      "dot_sign_consistent": true
    },
    {
      "from": "WVS_F|religious_belief",
      "to": "WVS_C|work_ethic",
      "gamma": 0.0128,
      "ci_lo": 0.0014,
      "ci_hi": 0.0276,
      "ci_width": 0.0262,
      "excl_zero": true,
      "nmi": 0.0,
      "fingerprint_dot": 0.008525,
      "fingerprint_cos": 0.564284,
      "dot_sign_consistent": true
    },
    {
      "from": "WVS_E|science_technology_optimism",
      "to": "WVS_C|work_ethic",
      "gamma": -0.0144,
      "ci_lo": -0.0246,
      "ci_hi": -0.0036,
      "ci_width": 0.021,
      "excl_zero": true,
      "nmi": 0.0001,
      "fingerprint_dot": -0.014956,
      "fingerprint_cos": -0.942954,
      "dot_sign_consistent": true
    }
  ]
}